{"steam:11000011777c126":{"cinematic":false,"speedtype":"kmh","compassPos":"top","showcompass":true,"hud":"texthud","hide":false},"license:299055de10756b9de64a546e74309416fc77059f":{"cinematic":false,"speedtype":"kmh","compassPos":"onmap","showcompass":true,"hud":"texthud","hide":false},"steam:1100001158a2a55":{"cinematic":false,"speedtype":"kmh","compassPos":"top","showcompass":true,"hud":"radialhud","hide":false},"steam:11000010affb348":{"cinematic":false,"speedtype":"kmh","compassPos":"top","showcompass":false,"hud":"texthud","hide":false},"license:e4ca622436d0caaf0a1a50a38eb925a893e440b7":{"cinematic":false,"speedtype":"kmh","compassPos":"top","showcompass":true,"hud":"texthud","hide":false},"license:519d6a1ff3f7c54eab8a720fbee20877afe22611":{"cinematic":false,"speedtype":"kmh","compassPos":"top","showcompass":true,"hud":"texthud","hide":false},"license:1d62627b16665d07c4946275c3e66dff30192741":{"cinematic":false,"speedtype":"mph","compassPos":"top","showcompass":true,"hud":"venicehud","hide":false}}