[{"name":"Ballas","id":"G0vNpF61nC1S9QeTsrNd4"},{"name":"Paleto PD","id":"htC-YyDBSTpYJtrEtx2zy"},{"name":"Sandy PD","id":"AD4qwYLXAKypphlNu5wqS"},{"name":"Town Hall","id":"cLL424MMmcZ4DPxvx3s5S"},{"name":"Pillbox","id":"lJAMI9VlSXg0eB1gqNMs4"},{"name":"La Mesa PD","id":"LlVHvT-fmDOCu6whFbohu"},{"name":"MRPD","id":"GmAciGjbgZ9uUzbMmCZOl"},{"name":"Premium Deluxe Motorsport","id":"eG6eHtn9xxiRmnI0gvXk3"},{"name":"Ottos","id":"M3cGu0Zu1u3teq5Sp4uad"},{"name":"Davis PD","id":"5Ts6ozupBjlUdNgPlcpde"},{"name":"LS Customs","id":"bhFjxMeME8UU1ukG0S6r4"},{"name":"Hayes Auto","id":"4hjXIcMPCThtf8Xiev6mG"},{"name":"Tuner Shop","id":"41HH4LIZkH5Q_t2dGfns7"},{"name":"PDM - LUXURY","id":"pWJA5gn-VCl3NwiiVY6WW"}]